easyconfig2/__init__.py
easyconfig2/easyconfig.py
easyconfig2/easydependency.py
easyconfig2/easydialog.py
easyconfig2/easynodes.py
easyconfig2/easytree.py
easyconfig2/easyutils.py
easyconfig2/easywidgets.py
easyconfig2/main.py
easyconfig2/tripledict.py
easyconfig2-0.0.1.dist-info/AUTHORS.rst
easyconfig2-0.0.1.dist-info/LICENSE
easyconfig2-0.0.1.dist-info/METADATA
easyconfig2-0.0.1.dist-info/WHEEL
easyconfig2-0.0.1.dist-info/top_level.txt
easyconfig2-0.0.1.dist-info/RECORD
