Metadata-Version: 2.2
Name: easyconfig2
Version: 0.0.1
Summary: A library for easy configuration v2
Home-page: https://github.com/dantard/easyconfig
Author: Danilo Tardioli
Author-email: dantard@unizar.es
Classifier: Programming Language :: Python :: 3
Classifier: License :: OSI Approved :: MIT License
Classifier: Operating System :: OS Independent
Requires-Python: >=3.10
License-File: LICENSE
License-File: AUTHORS.rst
Requires-Dist: pyqt5
Requires-Dist: pyyaml
Dynamic: author
Dynamic: author-email
Dynamic: classifier
Dynamic: description
Dynamic: description-content-type
Dynamic: home-page
Dynamic: requires-dist
Dynamic: requires-python
Dynamic: summary
